{
    "fields": [
        {
            "name": "nome",
            "type": "string"
        },
        {
            "name": "sobrenome",
            "type": "string"
        },
        {
            "name": "cpf",
            "type": "string"
        },
        {
            "name": "data_nascimento",
            "type": "date"
        },
        {
            "name": "celular",
            "type": "string"
        },
        {
            "name": "rua",
            "type": "string"
        },
        {
            "name": "cidade",
            "type": "string"
        },
        {
            "name": "estado",
            "type": "string"
        },
        {
            "name": "email",
            "type": "string"
        },
        {
            "name": "senha",
            "type": "string"
        }
    ]
}